trajectory_simulator/__init__.py
trajectory_simulator/arcgis_elevation_provider.py
trajectory_simulator/config.py
trajectory_simulator/elevation_provider.py
trajectory_simulator/gps_device.py
trajectory_simulator/gpx_trajectory_observer.py
trajectory_simulator/inspection_task.py
trajectory_simulator/main.py
trajectory_simulator/person.py
trajectory_simulator/trajectory_simulator.py
trajectory_simulator/config/__init__.py
trajectory_simulator/config/config.py
trajectory_simulator/gps/__init__.py
trajectory_simulator/gps/advanced_gps_device.py
trajectory_simulator/gps/gps_device.py
trajectory_simulator/gps/gps_device_factory.py
trajectory_simulator/gps/gps_observer.py
trajectory_simulator/gps/sampling_strategy.py
trajectory_simulator/observers/__init__.py
trajectory_simulator/observers/console_trajectory_observer.py
trajectory_simulator/observers/file_trajectory_observer.py
trajectory_simulator/observers/gpx_trajectory_observer.py
trajectory_simulator/observers/trajectory_observer.py
trajectory_simulator/person/__init__.py
trajectory_simulator/person/person.py
trajectory_simulator/terrain/__init__.py
trajectory_simulator/terrain/arcgis_elevation_provider.py
trajectory_simulator/terrain/elevation_provider.py
trajectory_simulator-1.0.2.dist-info/LICENSE
trajectory_simulator-1.0.2.dist-info/METADATA
trajectory_simulator-1.0.2.dist-info/WHEEL
trajectory_simulator-1.0.2.dist-info/top_level.txt
trajectory_simulator-1.0.2.dist-info/RECORD
