Metadata-Version: 2.1
Name: trajectory-simulator
Version: 1.0.2
Summary: A trajectory simulation package. Add elevation data to trajectory.
Home-page: 
Author: sgc
Author-email: s944804675@gmail.com
Classifier: Programming Language :: Python :: 3
Classifier: License :: OSI Approved :: MIT License
Classifier: Operating System :: OS Independent
License-File: LICENSE
Requires-Dist: shapely
